README.rst
setup.py
git_wipe/__init__.py
git_wipe/__main__.py
git_wipe/__version__.py
git_wipe/cli.py
git_wipe/env.py
git_wipe/github_client.py
git_wipe.egg-info/PKG-INFO
git_wipe.egg-info/SOURCES.txt
git_wipe.egg-info/dependency_links.txt
git_wipe.egg-info/entry_points.txt
git_wipe.egg-info/requires.txt
git_wipe.egg-info/top_level.txt